narada/__init__.py
narada/client.py
narada/py.typed
narada/utils.py
narada/version.py
narada/window.py
narada_pyodide-0.0.33.dist-info/METADATA
narada_pyodide-0.0.33.dist-info/WHEEL
narada_pyodide-0.0.33.dist-info/RECORD
