Metadata-Version: 2.4
Name: narada-pyodide
Version: 0.0.33
Summary: Pyodide-compatible Python client SDK for Narada
Project-URL: Homepage, https://github.com/NaradaAI/narada-python-sdk/packages/narada-pyodide
Project-URL: Repository, https://github.com/NaradaAI/narada-python-sdk
Project-URL: Issues, https://github.com/NaradaAI/narada-python-sdk/issues
Author-email: Narada <support@narada.ai>
License-Expression: Apache-2.0
Requires-Python: >=3.12
Requires-Dist: narada-core==0.0.9
Requires-Dist: semver>=3.0.4
